fbro/__init__.py
fbro/_version.py
fbro/aws.py
fbro/cli.py
fbro/interactive.py
fbro-0.1.6.dist-info/LICENSE
fbro-0.1.6.dist-info/METADATA
fbro-0.1.6.dist-info/WHEEL
fbro-0.1.6.dist-info/entry_points.txt
fbro-0.1.6.dist-info/top_level.txt
fbro-0.1.6.dist-info/RECORD
